setup.py
distribution_combo/Binomialdistribution.py
distribution_combo/Gaussiandistribution.py
distribution_combo/Generaldistribution.py
distribution_combo/__init__.py
distribution_combo.egg-info/PKG-INFO
distribution_combo.egg-info/SOURCES.txt
distribution_combo.egg-info/dependency_links.txt
distribution_combo.egg-info/not-zip-safe
distribution_combo.egg-info/top_level.txt